discord/ext/syntaxer/__init__.py
discord/ext/syntaxer/main.py
dpy_syntaxer-1.1.0.dist-info/LICENSE
dpy_syntaxer-1.1.0.dist-info/METADATA
dpy_syntaxer-1.1.0.dist-info/WHEEL
dpy_syntaxer-1.1.0.dist-info/top_level.txt
dpy_syntaxer-1.1.0.dist-info/RECORD
