Metadata-Version: 2.1
Name: dpy-syntaxer
Version: 1.1.0
Summary: Syntax maker for discord.py's command
Home-page: https://github.com/sevenc-nanashi/dpy-syntaxer
Author: sevenc-nanashi
Author-email: sevenc-nanashi@sevenbot.jp
License: UNKNOWN
Platform: UNKNOWN
Classifier: Programming Language :: Python :: 3.9
Classifier: License :: OSI Approved :: MIT License
Classifier: Operating System :: OS Independent
Requires-Dist: discord.py (>1.0.0<2.0.0)
